{
    "name": "One O Eight Forest",
    "tokenColors": [
        {
            "name": "Comments",
            "scope": [
                "comment"
            ],
            "settings": {
                "foreground": "#6E7B6E"
            }
        },
        {
            "name": "Punctuation",
            "scope": [
                "punctuation.definition"
            ],
            "settings": {
                "foreground": "#4B594A"
            }
        },
        {
            "name": "Types",
            "scope": [
                "support.type"
            ],
            "settings": {
                "foreground": "#405432"
            }
        },
        {
            "name": "Macro",
            "scope": [
                "support.function.macro"
            ],
            "settings": {
                "foreground": "#617256",
                "fontStyle": "italic"
            }
        },
        {
            "name": "Constant",
            "scope": [
                "constant"
            ],
            "settings": {
                "foreground": "#225846"
            }
        },
        {
            "name": "Constant (numeric)",
            "scope": [
                "constant.numeric"
            ],
            "settings": {
                "foreground": "#3E5B20"
            }
        },
        {
            "name": "Constant (escape char)",
            "scope": [
                "constant.character.escape"
            ],
            "settings": {
                "foreground": "#4B594A",
                "fontStyle": "bold italic"
            }
        },
        {
            "name": "Operator",
            "scope": [
                "keyword.operator"
            ],
            "settings": {
                "foreground": "#4B594A"
            }
        },
        {
            "name": "Operator (boolean)",
            "scope": [
                "keyword.operator.boolean"
            ],
            "settings": {
                "foreground": "#7A6F46"
            }
        },
        {
            "name": "Brackets",
            "scope": [
                "meta.bracket"
            ],
            "settings": {
                "foreground": "#6E7B6E"
            }
        },
        {
            "name": "String",
            "scope": [
                "string"
            ],
            "settings": {
                "foreground": "#607847"
            }
        },
        {
            "name": "Keywords",
            "scope": [
                "keyword"
            ],
            "settings": {
                "foreground": "#7E461C"
            }
        },
        {
            "name": "Interpolation",
            "scope": [
                "variable.interpolation"
            ],
            "settings": {
                "foreground": "#946644"
            }
        },
        {
            "name": "Function name",
            "scope": [
                "entity.name.function"
            ],
            "settings": {
                "foreground": "#5E501E",
                "fontStyle": "italic"
            }
        },
        {
            "name": "Function in code",
            "scope": [
                "support.function"
            ],
            "settings": {
                "foreground": "#5E501E"
            }
        },
        {
            "name": "TOML Section",
            "scope": [
                "entity.other.attribute-name.table.array.toml",
                "entity.other.attribute-name.table.toml"
            ],
            "settings": {
                "foreground": "#7E461C",
                "fontStyle": "bold"
            }
        },
        {
            "name": "Name tag entity",
            "scope": [
                "entity.name.tag"
            ],
            "settings": {
                "foreground": "#7E461C",
                "fontStyle": "bold"
            }
        },
        {
            "name": "Quoted YAML string",
            "scope": [
                "string.quoted.single.yaml",
                "string.quoted.double.yaml"
            ],
            "settings": {
                "foreground": "#5E501E"
            }
        },
        {
            "name": "Markdown title",
            "scope": [
                "markup.heading.markdown"
            ],
            "settings": {
                "foreground": "#5E501E",
                "fontStyle": "bold"
            }
        },
        {
            "name": "Markdown fenced block language",
            "scope": [
                "fenced_code.block.language"
            ],
            "settings": {
                "foreground": "#7E461C",
                "fontStyle": "italic"
            }
        },
        {
            "name": "Markdown link reference",
            "scope": [
                "string.other.link.title.markdown",
                "string.other.link.description.markdown"
            ],
            "settings": {
                "foreground": "#3E5B20",
                "fontStyle": "bold"
            }
        },
        {
            "name": "Markdown link reference",
            "scope": [
                "constant.other.reference.link.markdown"
            ],
            "settings": {
                "foreground": "#617256",
                "fontStyle": "italic"
            }
        },
        {
            "name": "Markdown actual link",
            "scope": [
                "markup.underline.link.markdown"
            ],
            "settings": {
                "foreground": "#7A6F46",
                "fontStyle": "underline"
            }
        },
        {
            "name": "Markdown raw code",
            "scope": [
                "markup.inline.raw.string.markdown"
            ],
            "settings": {
                "foreground": "#7E461C",
                "fontStyle": ""
            }
        },
        {
            "name": "Markdown bold",
            "scope": [
                "markup.bold"
            ],
            "settings": {
                "fontStyle": "bold"
            }
        },
        {
            "name": "Markdown italic",
            "scope": [
                "markup.italic"
            ],
            "settings": {
                "fontStyle": "italic"
            }
        },
        {
            "name": "Markdown citation",
            "scope": [
                "string.other.link.description.markdown.citation"
            ],
            "settings": {
                "foreground": "#4B594A",
                "fontStyle": "underline"
            }
        }
    ],
    "colors": {
        "gitDecoration.ignoredResourceForeground": "#C9B6B6",
        "tab.unfocusedActiveBackground": "#FCFBFB",
        "tab.inactiveBackground": "#D9CDCD",
        "notebookStatusErrorIcon.foreground": "#497566",
        "tab.border": "#EBE4E4",
        "editor.foreground": "#273A27",
        "notebook.focusedCellBorder": "#EBE4E4",
        "editorGroupHeader.tabsBackground": "#EBE4E4",
        "editorGutter.modifiedBackground": "#7A6F46",
        "icon.foreground": "#A68888",
        "editor.background": "#FCFBFB",
        "diffEditor.diagonalFill": "#6E7B6E44",
        "statusBar.background": "#EBE4E4",
        "gitDecoration.untrackedResourceForeground": "#7E461C",
        "activityBar.foreground": "#A68888",
        "gitDecoration.addedResourceForeground": "#3E5B20",
        "editor.selectionBackground": "#919B9166",
        "editorGutter.addedBackground": "#607847",
        "editor.lineHighlightBorder": "#FCFBFB",
        "notebookStatusSuccessIcon.foreground": "#607847",
        "editorGutter.deletedBackground": "#497566",
        "titleBar.activeBackground": "#EBE4E4",
        "sideBar.border": "#EBE4E4",
        "notebook.cellHoverBackground": "#EBE4E455",
        "gitDecoration.modifiedResourceForeground": "#5E501E",
        "editorLineNumber.foreground": "#6E7B6E",
        "foreground": "#273A27",
        "notebook.focusedEditorBorder": "#7E461C",
        "editorCursor.foreground": "#4B594A",
        "sideBar.background": "#EBE4E4",
        "notebookStatusRunningIcon.foreground": "#7A6F46",
        "list.highlightForeground": "#273A27",
        "tab.activeBorderTop": "#946644",
        "notebook.focusedCellBackground": "#EBE4E4",
        "sideBar.dropBackground": "#946644",
        "statusBar.foreground": "#273A27",
        "editorLineNumber.activeForeground": "#4B594A",
        "diffEditor.removedTextBackground": "#61725622",
        "titleBar.inactiveBackground": "#EBE4E4",
        "diffEditor.insertedTextBackground": "#7A6F4622",
        "activityBar.background": "#EBE4E4",
        "editorGroup.border": "#EBE4E4",
        "gitDecoration.deletedResourceForeground": "#225846"
    },
    "type": "light"
}
