{
    "name": "One O Eight Safe",
    "tokenColors": [
        {
            "name": "Comments",
            "scope": [
                "comment"
            ],
            "settings": {
                "foreground": "#6A6A6A"
            }
        },
        {
            "name": "Types",
            "scope": [
                "support.type"
            ],
            "settings": {
                "foreground": "#FE6100"
            }
        },
        {
            "name": "Macro",
            "scope": [
                "support.function.macro"
            ],
            "settings": {
                "foreground": "#E24D96",
                "fontStyle": "italic"
            }
        },
        {
            "name": "Constant",
            "scope": [
                "constant"
            ],
            "settings": {
                "foreground": "#DC267F"
            }
        },
        {
            "name": "Constant (numeric)",
            "scope": [
                "constant.numeric"
            ],
            "settings": {
                "foreground": "#FFB000"
            }
        },
        {
            "name": "Constant (escape char)",
            "scope": [
                "constant.character.escape"
            ],
            "settings": {
                "foreground": "#464646",
                "fontStyle": "bold italic"
            }
        },
        {
            "name": "Operator",
            "scope": [
                "keyword.operator"
            ],
            "settings": {
                "foreground": "#464646"
            }
        },
        {
            "name": "Operator (boolean)",
            "scope": [
                "keyword.operator.boolean"
            ],
            "settings": {
                "foreground": "#80A3FF"
            }
        },
        {
            "name": "Brackets",
            "scope": [
                "meta.bracket"
            ],
            "settings": {
                "foreground": "#6A6A6A"
            }
        },
        {
            "name": "String",
            "scope": [
                "string"
            ],
            "settings": {
                "foreground": "#FFBE2E"
            }
        },
        {
            "name": "Keywords",
            "scope": [
                "keyword"
            ],
            "settings": {
                "foreground": "#785EF0"
            }
        },
        {
            "name": "Interpolation",
            "scope": [
                "variable.interpolation"
            ],
            "settings": {
                "foreground": "#907BF3"
            }
        },
        {
            "name": "Function name",
            "scope": [
                "entity.name.function"
            ],
            "settings": {
                "foreground": "#648FFF",
                "fontStyle": "italic"
            }
        },
        {
            "name": "Function in code",
            "scope": [
                "support.function"
            ],
            "settings": {
                "foreground": "#648FFF"
            }
        },
        {
            "name": "TOML Section",
            "scope": [
                "entity.other.attribute-name.table.array.toml",
                "entity.other.attribute-name.table.toml"
            ],
            "settings": {
                "foreground": "#785EF0",
                "fontStyle": "bold"
            }
        },
        {
            "name": "Name tag entity",
            "scope": [
                "entity.name.tag"
            ],
            "settings": {
                "foreground": "#785EF0",
                "fontStyle": "bold"
            }
        },
        {
            "name": "Quoted YAML string",
            "scope": [
                "string.quoted.single.yaml",
                "string.quoted.double.yaml"
            ],
            "settings": {
                "foreground": "#648FFF"
            }
        },
        {
            "name": "Markdown title",
            "scope": [
                "markup.heading.markdown"
            ],
            "settings": {
                "foreground": "#648FFF",
                "fontStyle": "bold"
            }
        },
        {
            "name": "Markdown fenced block language",
            "scope": [
                "fenced_code.block.language"
            ],
            "settings": {
                "foreground": "#785EF0",
                "fontStyle": "italic"
            }
        },
        {
            "name": "Markdown link reference",
            "scope": [
                "string.other.link.title.markdown",
                "string.other.link.description.markdown"
            ],
            "settings": {
                "foreground": "#FFB000",
                "fontStyle": "bold"
            }
        },
        {
            "name": "Markdown link reference",
            "scope": [
                "constant.other.reference.link.markdown"
            ],
            "settings": {
                "foreground": "#FE7E2E",
                "fontStyle": "italic"
            }
        },
        {
            "name": "Markdown actual link",
            "scope": [
                "markup.underline.link.markdown"
            ],
            "settings": {
                "foreground": "#80A3FF",
                "fontStyle": "underline"
            }
        },
        {
            "name": "Markdown raw code",
            "scope": [
                "markup.inline.raw.string.markdown"
            ],
            "settings": {
                "foreground": "#785EF0",
                "fontStyle": ""
            }
        },
        {
            "name": "Markdown bold",
            "scope": [
                "markup.bold"
            ],
            "settings": {
                "fontStyle": "bold"
            }
        },
        {
            "name": "Markdown italic",
            "scope": [
                "markup.italic"
            ],
            "settings": {
                "fontStyle": "italic"
            }
        },
        {
            "name": "Markdown citation",
            "scope": [
                "string.other.link.description.markdown.citation"
            ],
            "settings": {
                "foreground": "#464646",
                "fontStyle": "underline"
            }
        },
        {
            "name": "Punctuation",
            "scope": [
                "punctuation.definition"
            ],
            "settings": {
                "foreground": "#464646"
            }
        }
    ],
    "colors": {
        "gitDecoration.ignoredResourceForeground": "#B9B9B9",
        "tab.unfocusedActiveBackground": "#FDFDFD",
        "tab.inactiveBackground": "#CBCBCB",
        "notebookStatusErrorIcon.foreground": "#E24D96",
        "tab.border": "#DCDCDC",
        "badge.foreground": "#212121",
        "badge.background": "#907BF3",
        "editor.foreground": "#212121",
        "notebook.focusedCellBorder": "#DCDCDC",
        "editorGroupHeader.tabsBackground": "#DCDCDC",
        "editorGutter.modifiedBackground": "#80A3FF",
        "icon.foreground": "#907BF3",
        "editor.background": "#FDFDFD",
        "diffEditor.diagonalFill": "#6A6A6A44",
        "statusBar.background": "#DCDCDC",
        "gitDecoration.untrackedResourceForeground": "#785EF0",
        "activityBar.foreground": "#907BF3",
        "gitDecoration.addedResourceForeground": "#FFB000",
        "editor.selectionBackground": "#8F8F8F66",
        "editorGutter.addedBackground": "#FFBE2E",
        "editor.lineHighlightBorder": "#FDFDFD",
        "notebookStatusSuccessIcon.foreground": "#FFBE2E",
        "editorGutter.deletedBackground": "#E24D96",
        "titleBar.activeBackground": "#DCDCDC",
        "sideBar.border": "#DCDCDC",
        "notebook.cellHoverBackground": "#DCDCDC55",
        "gitDecoration.modifiedResourceForeground": "#648FFF",
        "editorLineNumber.foreground": "#8F8F8F",
        "foreground": "#212121",
        "notebook.focusedEditorBorder": "#785EF0",
        "editorCursor.foreground": "#464646",
        "activityBar.inactiveForeground": "#A9A9A9",
        "sideBar.background": "#DCDCDC",
        "notebookStatusRunningIcon.foreground": "#80A3FF",
        "list.highlightForeground": "#212121",
        "tab.activeBorderTop": "#907BF3",
        "notebook.focusedCellBackground": "#DCDCDC",
        "sideBar.dropBackground": "#907BF3",
        "statusBar.foreground": "#212121",
        "editorLineNumber.activeForeground": "#464646",
        "diffEditor.removedTextBackground": "#FE7E2E22",
        "titleBar.inactiveBackground": "#DCDCDC",
        "diffEditor.insertedTextBackground": "#80A3FF22",
        "activityBar.background": "#DCDCDC",
        "editorGroup.border": "#DCDCDC",
        "gitDecoration.deletedResourceForeground": "#DC267F"
    },
    "type": "light"
}
