{
    "name": "One O Eight Seaside",
    "tokenColors": [
        {
            "name": "Comments",
            "scope": [
                "comment"
            ],
            "settings": {
                "foreground": "#505050"
            }
        },
        {
            "name": "Punctuation",
            "scope": [
                "punctuation.definition"
            ],
            "settings": {
                "foreground": "#959595"
            }
        },
        {
            "name": "Types",
            "scope": [
                "support.type"
            ],
            "settings": {
                "foreground": "#3FA382"
            }
        },
        {
            "name": "Macro",
            "scope": [
                "support.function.macro"
            ],
            "settings": {
                "foreground": "#64B49A",
                "fontStyle": "italic"
            }
        },
        {
            "name": "Constant",
            "scope": [
                "constant"
            ],
            "settings": {
                "foreground": "#387E62"
            }
        },
        {
            "name": "Constant (numeric)",
            "scope": [
                "constant.numeric"
            ],
            "settings": {
                "foreground": "#D79C65"
            }
        },
        {
            "name": "Constant (escape char)",
            "scope": [
                "constant.character.escape"
            ],
            "settings": {
                "foreground": "#505050",
                "fontStyle": "bold italic"
            }
        },
        {
            "name": "Operator",
            "scope": [
                "keyword.operator"
            ],
            "settings": {
                "foreground": "#505050"
            }
        },
        {
            "name": "Operator (boolean)",
            "scope": [
                "keyword.operator.boolean"
            ],
            "settings": {
                "foreground": "#5A97DD"
            }
        },
        {
            "name": "Brackets",
            "scope": [
                "meta.bracket"
            ],
            "settings": {
                "foreground": "#737373"
            }
        },
        {
            "name": "String",
            "scope": [
                "string"
            ],
            "settings": {
                "foreground": "#DEAF83"
            }
        },
        {
            "name": "Keywords",
            "scope": [
                "keyword"
            ],
            "settings": {
                "foreground": "#1F9DB4"
            }
        },
        {
            "name": "Interpolation",
            "scope": [
                "variable.interpolation"
            ],
            "settings": {
                "foreground": "#4BB0C2"
            }
        },
        {
            "name": "Function name",
            "scope": [
                "entity.name.function"
            ],
            "settings": {
                "foreground": "#327ED6",
                "fontStyle": "italic"
            }
        },
        {
            "name": "Function in code",
            "scope": [
                "support.function"
            ],
            "settings": {
                "foreground": "#327ED6"
            }
        },
        {
            "name": "TOML Section",
            "scope": [
                "entity.other.attribute-name.table.array.toml",
                "entity.other.attribute-name.table.toml"
            ],
            "settings": {
                "foreground": "#1F9DB4",
                "fontStyle": "bold"
            }
        },
        {
            "name": "Name tag entity",
            "scope": [
                "entity.name.tag"
            ],
            "settings": {
                "foreground": "#1F9DB4",
                "fontStyle": "bold"
            }
        },
        {
            "name": "Quoted YAML string",
            "scope": [
                "string.quoted.single.yaml",
                "string.quoted.double.yaml"
            ],
            "settings": {
                "foreground": "#327ED6"
            }
        },
        {
            "name": "Markdown title",
            "scope": [
                "markup.heading.markdown"
            ],
            "settings": {
                "foreground": "#327ED6",
                "fontStyle": "bold"
            }
        },
        {
            "name": "Markdown fenced block language",
            "scope": [
                "fenced_code.block.language"
            ],
            "settings": {
                "foreground": "#1F9DB4",
                "fontStyle": "italic"
            }
        },
        {
            "name": "Markdown link reference",
            "scope": [
                "string.other.link.title.markdown",
                "string.other.link.description.markdown"
            ],
            "settings": {
                "foreground": "#D79C65",
                "fontStyle": "bold"
            }
        },
        {
            "name": "Markdown link reference",
            "scope": [
                "constant.other.reference.link.markdown"
            ],
            "settings": {
                "foreground": "#64B49A",
                "fontStyle": "italic"
            }
        },
        {
            "name": "Markdown actual link",
            "scope": [
                "markup.underline.link.markdown"
            ],
            "settings": {
                "foreground": "#5A97DD",
                "fontStyle": "underline"
            }
        },
        {
            "name": "Markdown raw code",
            "scope": [
                "markup.inline.raw.string.markdown"
            ],
            "settings": {
                "foreground": "#1F9DB4",
                "fontStyle": ""
            }
        },
        {
            "name": "Markdown bold",
            "scope": [
                "markup.bold"
            ],
            "settings": {
                "fontStyle": "bold"
            }
        },
        {
            "name": "Markdown italic",
            "scope": [
                "markup.italic"
            ],
            "settings": {
                "fontStyle": "italic"
            }
        },
        {
            "name": "Markdown citation",
            "scope": [
                "string.other.link.description.markdown.citation"
            ],
            "settings": {
                "foreground": "#505050",
                "fontStyle": "underline"
            }
        }
    ],
    "colors": {
        "gitDecoration.ignoredResourceForeground": "#959595",
        "tab.unfocusedActiveBackground": "#FBFBFB",
        "tab.inactiveBackground": "#CECECE",
        "notebookStatusErrorIcon.foreground": "#5F9780",
        "tab.border": "#E5E5E5",
        "editor.foreground": "#2F2F2F",
        "notebook.focusedCellBorder": "#E5E5E5",
        "editorGroupHeader.tabsBackground": "#E5E5E5",
        "editorGutter.modifiedBackground": "#5A97DD",
        "icon.foreground": "#505050",
        "editor.background": "#FBFBFB",
        "diffEditor.diagonalFill": "#B7B7B744",
        "statusBar.background": "#E5E5E5",
        "gitDecoration.untrackedResourceForeground": "#1F9DB4",
        "activityBar.foreground": "#505050",
        "gitDecoration.addedResourceForeground": "#D79C65",
        "editor.selectionBackground": "#95959566",
        "editorGutter.addedBackground": "#DEAF83",
        "editor.lineHighlightBorder": "#FBFBFB",
        "notebookStatusSuccessIcon.foreground": "#DEAF83",
        "editorGutter.deletedBackground": "#5F9780",
        "titleBar.activeBackground": "#E5E5E5",
        "sideBar.border": "#E5E5E5",
        "notebook.cellHoverBackground": "#E5E5E555",
        "gitDecoration.modifiedResourceForeground": "#327ED6",
        "editorLineNumber.foreground": "#B7B7B7",
        "foreground": "#2F2F2F",
        "notebook.focusedEditorBorder": "#1F9DB4",
        "editorCursor.foreground": "#3FA382",
        "sideBar.background": "#E5E5E5",
        "notebookStatusRunningIcon.foreground": "#5A97DD",
        "list.highlightForeground": "#2F2F2F",
        "tab.activeBorderTop": "#4BB0C2",
        "notebook.focusedCellBackground": "#E5E5E5",
        "sideBar.dropBackground": "#4BB0C2",
        "statusBar.foreground": "#2F2F2F",
        "editorLineNumber.activeForeground": "#737373",
        "diffEditor.removedTextBackground": "#64B49A22",
        "titleBar.inactiveBackground": "#E5E5E5",
        "diffEditor.insertedTextBackground": "#5A97DD22",
        "activityBar.background": "#E5E5E5",
        "editorGroup.border": "#E5E5E5",
        "gitDecoration.deletedResourceForeground": "#387E62"
    },
    "type": "light"
}
